pylite3/__init__.pyi
pylite3/_core.cpython-311-i386-linux-musl.so
pylite3/py.typed
pylite3/__init__.py
pylite3-0.0.1.dist-info/WHEEL
pylite3-0.0.1.dist-info/top_level.txt
pylite3-0.0.1.dist-info/METADATA
pylite3-0.0.1.dist-info/RECORD
