Metadata-Version: 2.4
Name: pylite3
Version: 0.0.1
Summary: Fast Python bindings for lite3 using zero-copy lazy parsing
Author-email: Tri Songz <ts@songzcorp.com>
Project-URL: Homepage, https://github.com/fastserial/pylite3
Project-URL: Repository, https://github.com/fastserial/pylite3
Classifier: Programming Language :: Python :: 3
Classifier: Programming Language :: Python :: 3 :: Only
Classifier: Programming Language :: Python :: Implementation :: CPython
Classifier: Programming Language :: C
Classifier: Operating System :: OS Independent
Requires-Python: >=3.9
